{ "backgroundcolor":"#000000",
 "height":60,
 "infinite":false,
 "layers":[
        {
         "compression":"zlib",
         "data":"eJzt3dFxm0AYhVHKiFJYnlSGC1AFqiRlpBt7xi04k8jjDYZdcID9lz3fzHmRHZsn7oCQ8zIMtxcAAAAAAAAAAAAAAAAAAAAAAAAAAAAAAABgM8\/DMEyRju7629PDtfKxLK3FY5bmWrsbUpRaPBe3eMxSqSX7IR3dz41EyX60368R\/c21h6J1LUjPxTlRsh9tN94OG\/KR\/VC07g\/vO3AfvZaei8dfS1+Lkv1ot7ntsCEf5d4vl46ulf3Y6j5b9PtvPWc\/ytkPRaqV\/SjdP\/vKPbeI9996zn6Uex3+3RD7oZq18v7Hfcjv15LNy\/071e8yzF8fXioeV7Ryn\/eQjqyV6w\/7cZ4uG+st+6Eo2Y\/Px\/9jBa0vPfdPXWdMyX1fb9kPtVCkZ5nsx7n6VvC+E6Xv6zH7oRbaYj+2eibKfpyv3HsduWuP3p+Zsx9qoS32Y80zULn35KPuh2e4dHT2QzU78rMUS87fS87pe+9HugP2Q5GzH6rZkZ+lsB\/SttkP1WzNOX28H3uc9+2HtDz7oZrZj332o\/Ss0N7UR\/ZDNbMfs6\/fpr6Wk+7H98rUR\/ZDNWtxP6L+DcR0d+yHjsh+qGZ778fjfPrH\/+xH+nOekmOZEqG9n2uLtJuql\/1Qzeaem\/rqfky4JRb\/rtzPyd1Dknoq3Y\/xhkh7Zz+kdrMfqtlZ7l9JvTXejql7WPZEe9bifrjnL5X\/D3T7obOX7lKEv+0rtZL9UO\/ZD2l9c9uR2xDpbNkPaX2l\/QAAAAAAAAAAAAAAAAAAAAAAAAAAAAAAAAAAYF9vq9\/owg==",
         "encoding":"base64",
         "height":60,
         "name":"back",
         "opacity":0.5,
         "type":"tilelayer",
         "visible":true,
         "width":400,
         "x":0,
         "y":0
        }, 
        {
         "compression":"zlib",
         "data":"eJzt29FNwzAUBdCMQRmML4Zhgk7CGPwxAOuQSFRNg9vabhw77jnSUwQK5sGHb+3EwwAAAAAAAAAAAAAAAAAAAAAAAAAAAAAAAABA647D8PE+XmNruv\/RMbauNXoOjQHwzELz6PS9W\/U93jOve\/e3kB+hnuUHQL5r+VFyfOsPcnwtCqhLfsiPPQjlhQyBunLyY7kXlDr+mrkQW6l7bsv9N\/lRz62ckCFQz57XH1vM6fKjPvkBbZIfcf3Lj3rkB7Rp7\/tXsX9nSs+h\/lPz4xgo8hzG+vyrk9PXhyodARPrj7j+p+vPeI2t47lH7jgULqAM+RHX\/3R9G6+xJT+A3p3mueW8XPL8YMq7T1eqyv6V\/AA4C+VH6mf+rc9S5OTHA78r+\/mH\/AB6Np+LYyswxqZnKeQHQH219oISfmyVcXJ7BiBsD5\/lS40DQD75AUAO+1d9e6ndANAt64++vdZuAOhW7\/kxPzNSq2ppoQegXznvme5lLyj1bEuhM\/L\/\/l9blXeIgZJ6nWPWzo6a65c9r4GAfvWYHyXWHZ61AFzqbf+q1J6V\/AC41NP6o+TzDvkBcGmeH7Xr2jPg2Cr9HByAsxbeUbo1P7feH8Czan1+br0\/AAAAAAAAAAAAAAAAAAAAAAAAAAAAAAAAAADguf0C9huWjw==",
         "encoding":"base64",
         "height":60,
         "name":"front",
         "opacity":1,
         "type":"tilelayer",
         "visible":true,
         "width":400,
         "x":0,
         "y":0
        }, 
        {
         "color":"#5555ff",
         "draworder":"topdown",
         "name":"mods",
         "objects":[
                {
                 "height":8,
                 "id":1054,
                 "name":"",
                 "properties":
                    {
                     "back":"apexshipwall",
                     "colorVariant":"6"
                    },
                 "propertytypes":
                    {
                     "back":"string",
                     "colorVariant":"string"
                    },
                 "rotation":0,
                 "type":"",
                 "visible":true,
                 "width":32,
                 "x":1480,
                 "y":312
                }, 
                {
                 "height":8,
                 "id":1055,
                 "name":"",
                 "properties":
                    {
                     "back":"apexshipwall",
                     "colorVariant":"6"
                    },
                 "propertytypes":
                    {
                     "back":"string",
                     "colorVariant":"string"
                    },
                 "rotation":0,
                 "type":"",
                 "visible":true,
                 "width":32,
                 "x":1568,
                 "y":312
                }, 
                {
                 "height":8,
                 "id":1056,
                 "name":"",
                 "properties":
                    {
                     "back":"apexshipwall",
                     "colorVariant":"6"
                    },
                 "propertytypes":
                    {
                     "back":"string",
                     "colorVariant":"string"
                    },
                 "rotation":0,
                 "type":"",
                 "visible":true,
                 "width":24,
                 "x":1528,
                 "y":312
                }, 
                {
                 "height":8,
                 "id":1057,
                 "name":"",
                 "properties":
                    {
                     "back":"apexshipwall",
                     "colorVariant":"6"
                    },
                 "propertytypes":
                    {
                     "back":"string",
                     "colorVariant":"string"
                    },
                 "rotation":0,
                 "type":"",
                 "visible":true,
                 "width":32,
                 "x":1568,
                 "y":272
                }, 
                {
                 "height":8,
                 "id":1058,
                 "name":"",
                 "properties":
                    {
                     "back":"apexshipwall",
                     "colorVariant":"6"
                    },
                 "propertytypes":
                    {
                     "back":"string",
                     "colorVariant":"string"
                    },
                 "rotation":0,
                 "type":"",
                 "visible":true,
                 "width":24,
                 "x":1528,
                 "y":272
                }, 
                {
                 "height":8,
                 "id":1059,
                 "name":"",
                 "properties":
                    {
                     "back":"apexshipwall",
                     "colorVariant":"6"
                    },
                 "propertytypes":
                    {
                     "back":"string",
                     "colorVariant":"string"
                    },
                 "rotation":0,
                 "type":"",
                 "visible":true,
                 "width":32,
                 "x":1480,
                 "y":272
                }, 
                {
                 "height":8,
                 "id":1060,
                 "name":"",
                 "properties":
                    {
                     "back":"apexshipwall",
                     "colorVariant":"6"
                    },
                 "propertytypes":
                    {
                     "back":"string",
                     "colorVariant":"string"
                    },
                 "rotation":0,
                 "type":"",
                 "visible":true,
                 "width":32,
                 "x":1568,
                 "y":232
                }, 
                {
                 "height":8,
                 "id":1061,
                 "name":"",
                 "properties":
                    {
                     "back":"apexshipwall",
                     "colorVariant":"6"
                    },
                 "propertytypes":
                    {
                     "back":"string",
                     "colorVariant":"string"
                    },
                 "rotation":0,
                 "type":"",
                 "visible":true,
                 "width":24,
                 "x":1528,
                 "y":232
                }, 
                {
                 "height":8,
                 "id":1062,
                 "name":"",
                 "properties":
                    {
                     "back":"apexshipwall",
                     "colorVariant":"6"
                    },
                 "propertytypes":
                    {
                     "back":"string",
                     "colorVariant":"string"
                    },
                 "rotation":0,
                 "type":"",
                 "visible":true,
                 "width":32,
                 "x":1480,
                 "y":232
                }],
         "opacity":1,
         "type":"objectgroup",
         "visible":true,
         "x":0,
         "y":0
        }, 
        {
         "color":"#ff0000",
         "draworder":"topdown",
         "name":"objects",
         "objects":[
                {
                 "gid":5669,
                 "height":40,
                 "id":971,
                 "name":"",
                 "rotation":0,
                 "type":"",
                 "visible":true,
                 "width":40,
                 "x":1448,
                 "y":320
                }, 
                {
                 "gid":5669,
                 "height":40,
                 "id":972,
                 "name":"",
                 "rotation":0,
                 "type":"",
                 "visible":true,
                 "width":40,
                 "x":1592,
                 "y":320
                }, 
                {
                 "gid":6280,
                 "height":8,
                 "id":973,
                 "name":"",
                 "rotation":0,
                 "type":"",
                 "visible":true,
                 "width":16,
                 "x":1576,
                 "y":224
                }, 
                {
                 "gid":6280,
                 "height":8,
                 "id":974,
                 "name":"",
                 "rotation":0,
                 "type":"",
                 "visible":true,
                 "width":16,
                 "x":1488,
                 "y":224
                }, 
                {
                 "gid":6602,
                 "height":8,
                 "id":975,
                 "name":"",
                 "rotation":0,
                 "type":"",
                 "visible":true,
                 "width":16,
                 "x":1656,
                 "y":176
                }, 
                {
                 "gid":6602,
                 "height":8,
                 "id":976,
                 "name":"",
                 "rotation":0,
                 "type":"",
                 "visible":true,
                 "width":16,
                 "x":1768,
                 "y":176
                }, 
                {
                 "gid":6602,
                 "height":8,
                 "id":977,
                 "name":"",
                 "rotation":0,
                 "type":"",
                 "visible":true,
                 "width":16,
                 "x":1296,
                 "y":240
                }, 
                {
                 "gid":6602,
                 "height":8,
                 "id":978,
                 "name":"",
                 "rotation":0,
                 "type":"",
                 "visible":true,
                 "width":16,
                 "x":1408,
                 "y":240
                }, 
                {
                 "gid":6413,
                 "height":16,
                 "id":979,
                 "name":"",
                 "rotation":0,
                 "type":"",
                 "visible":true,
                 "width":16,
                 "x":1440,
                 "y":248
                }, 
                {
                 "gid":6412,
                 "height":16,
                 "id":980,
                 "name":"",
                 "rotation":0,
                 "type":"",
                 "visible":true,
                 "width":16,
                 "x":1624,
                 "y":184
                }, 
                {
                 "gid":6602,
                 "height":8,
                 "id":983,
                 "name":"",
                 "rotation":0,
                 "type":"",
                 "visible":true,
                 "width":16,
                 "x":1400,
                 "y":152
                }, 
                {
                 "gid":6602,
                 "height":8,
                 "id":984,
                 "name":"",
                 "rotation":0,
                 "type":"",
                 "visible":true,
                 "width":16,
                 "x":1304,
                 "y":152
                }, 
                {
                 "gid":6411,
                 "height":16,
                 "id":985,
                 "name":"",
                 "rotation":0,
                 "type":"",
                 "visible":true,
                 "width":24,
                 "x":1528,
                 "y":232
                }, 
                {
                 "gid":2147486337,
                 "height":16,
                 "id":986,
                 "name":"",
                 "rotation":0,
                 "type":"",
                 "visible":true,
                 "width":16,
                 "x":1432,
                 "y":272
                }, 
                {
                 "gid":2689,
                 "height":16,
                 "id":987,
                 "name":"",
                 "rotation":0,
                 "type":"",
                 "visible":true,
                 "width":16,
                 "x":1632,
                 "y":208
                }, 
                {
                 "gid":2147486348,
                 "height":32,
                 "id":996,
                 "name":"",
                 "rotation":0,
                 "type":"",
                 "visible":true,
                 "width":16,
                 "x":1416,
                 "y":208
                }, 
                {
                 "gid":2796,
                 "height":48,
                 "id":998,
                 "name":"",
                 "rotation":0,
                 "type":"",
                 "visible":true,
                 "width":32,
                 "x":1264,
                 "y":320
                }, 
                {
                 "gid":2703,
                 "height":18,
                 "id":999,
                 "name":"",
                 "rotation":0,
                 "type":"",
                 "visible":true,
                 "width":15,
                 "x":1392,
                 "y":208
                }, 
                {
                 "gid":2700,
                 "height":32,
                 "id":1001,
                 "name":"",
                 "rotation":0,
                 "type":"",
                 "visible":true,
                 "width":16,
                 "x":1288,
                 "y":208
                }, 
                {
                 "gid":2147486351,
                 "height":18,
                 "id":1002,
                 "name":"",
                 "rotation":0,
                 "type":"",
                 "visible":true,
                 "width":15,
                 "x":1312,
                 "y":208
                }, 
                {
                 "gid":2542,
                 "height":40,
                 "id":1005,
                 "name":"",
                 "properties":
                    {
                     "parameters":"{ \"treasurePools\" : [ \"atprk_apexarea48Treasure\" ] }"
                    },
                 "propertytypes":
                    {
                     "parameters":"string"
                    },
                 "rotation":0,
                 "type":"",
                 "visible":true,
                 "width":32,
                 "x":1392,
                 "y":320
                }, 
                {
                 "gid":2542,
                 "height":40,
                 "id":1006,
                 "name":"",
                 "properties":
                    {
                     "parameters":"{ \"treasurePools\" : [ \"atprk_apexarea48Treasure\" ] }"
                    },
                 "propertytypes":
                    {
                     "parameters":"string"
                    },
                 "rotation":0,
                 "type":"",
                 "visible":true,
                 "width":32,
                 "x":1296,
                 "y":320
                }, 
                {
                 "gid":2692,
                 "height":8,
                 "id":1008,
                 "name":"",
                 "rotation":0,
                 "type":"",
                 "visible":true,
                 "width":24,
                 "x":1568,
                 "y":288
                }, 
                {
                 "gid":2147486340,
                 "height":8,
                 "id":1009,
                 "name":"",
                 "rotation":0,
                 "type":"",
                 "visible":true,
                 "width":24,
                 "x":1488,
                 "y":288
                }, 
                {
                 "gid":2624,
                 "height":24,
                 "id":1010,
                 "name":"",
                 "rotation":0,
                 "type":"",
                 "visible":true,
                 "width":24,
                 "x":1528,
                 "y":272
                }, 
                {
                 "gid":250,
                 "height":8,
                 "id":1014,
                 "name":"",
                 "rotation":0,
                 "type":"",
                 "visible":true,
                 "width":8,
                 "x":1536,
                 "y":352
                }, 
                {
                 "gid":2689,
                 "height":16,
                 "id":1017,
                 "name":"",
                 "rotation":0,
                 "type":"",
                 "visible":true,
                 "width":16,
                 "x":1632,
                 "y":264
                }, 
                {
                 "gid":6383,
                 "height":16,
                 "id":1018,
                 "name":"",
                 "rotation":0,
                 "type":"",
                 "visible":true,
                 "width":16,
                 "x":1840,
                 "y":312
                }, 
                {
                 "gid":6383,
                 "height":16,
                 "id":1019,
                 "name":"",
                 "rotation":0,
                 "type":"",
                 "visible":true,
                 "width":16,
                 "x":1952,
                 "y":208
                }, 
                {
                 "gid":5687,
                 "height":40,
                 "id":1020,
                 "name":"",
                 "rotation":0,
                 "type":"",
                 "visible":true,
                 "width":8,
                 "x":1824,
                 "y":272
                }, 
                {
                 "gid":7772,
                 "height":8,
                 "id":1022,
                 "name":"",
                 "rotation":0,
                 "type":"",
                 "visible":true,
                 "width":8,
                 "x":1832,
                 "y":256
                }, 
                {
                 "gid":7772,
                 "height":8,
                 "id":1023,
                 "name":"",
                 "rotation":0,
                 "type":"",
                 "visible":true,
                 "width":8,
                 "x":1816,
                 "y":256
                }, 
                {
                 "gid":5687,
                 "height":40,
                 "id":1028,
                 "name":"",
                 "rotation":0,
                 "type":"",
                 "visible":true,
                 "width":8,
                 "x":1936,
                 "y":272
                }, 
                {
                 "gid":7772,
                 "height":8,
                 "id":1029,
                 "name":"",
                 "rotation":0,
                 "type":"",
                 "visible":true,
                 "width":8,
                 "x":1928,
                 "y":256
                }, 
                {
                 "gid":7772,
                 "height":8,
                 "id":1030,
                 "name":"",
                 "rotation":0,
                 "type":"",
                 "visible":true,
                 "width":8,
                 "x":1944,
                 "y":256
                }, 
                {
                 "gid":2634,
                 "height":16,
                 "id":1031,
                 "name":"",
                 "properties":
                    {
                     "parameters":"{ \"treasurePools\" : [ \"atprk_apexarea48Treasure\" ] }"
                    },
                 "propertytypes":
                    {
                     "parameters":"string"
                    },
                 "rotation":0,
                 "type":"",
                 "visible":true,
                 "width":40,
                 "x":1744,
                 "y":272
                }, 
                {
                 "gid":2147486351,
                 "height":18,
                 "id":1032,
                 "name":"",
                 "rotation":0,
                 "type":"",
                 "visible":true,
                 "width":15,
                 "x":1784,
                 "y":272
                }, 
                {
                 "gid":8812,
                 "height":16,
                 "id":1033,
                 "name":"",
                 "rotation":0,
                 "type":"",
                 "visible":true,
                 "width":16,
                 "x":1760,
                 "y":256
                }, 
                {
                 "gid":8838,
                 "height":18,
                 "id":1035,
                 "name":"",
                 "rotation":0,
                 "type":"",
                 "visible":true,
                 "width":48,
                 "x":2560,
                 "y":224
                }, 
                {
                 "gid":8838,
                 "height":18,
                 "id":1036,
                 "name":"",
                 "rotation":0,
                 "type":"",
                 "visible":true,
                 "width":48,
                 "x":2640,
                 "y":224
                }, 
                {
                 "gid":8835,
                 "height":40,
                 "id":1037,
                 "name":"",
                 "rotation":0,
                 "type":"",
                 "visible":true,
                 "width":48,
                 "x":2656,
                 "y":192
                }, 
                {
                 "gid":2147492483,
                 "height":40,
                 "id":1038,
                 "name":"",
                 "rotation":0,
                 "type":"",
                 "visible":true,
                 "width":48,
                 "x":2544,
                 "y":192
                }, 
                {
                 "gid":8836,
                 "height":16,
                 "id":1039,
                 "name":"",
                 "rotation":0,
                 "type":"",
                 "visible":true,
                 "width":16,
                 "x":2600,
                 "y":184
                }, 
                {
                 "gid":2147492484,
                 "height":16,
                 "id":1040,
                 "name":"",
                 "rotation":0,
                 "type":"",
                 "visible":true,
                 "width":16,
                 "x":2632,
                 "y":184
                }, 
                {
                 "gid":5934,
                 "height":24,
                 "id":1041,
                 "name":"",
                 "rotation":0,
                 "type":"",
                 "visible":true,
                 "width":16,
                 "x":2616,
                 "y":192
                }, 
                {
                 "gid":6301,
                 "height":8,
                 "id":1044,
                 "name":"",
                 "rotation":0,
                 "type":"",
                 "visible":true,
                 "width":8,
                 "x":2520,
                 "y":200
                }, 
                {
                 "gid":6303,
                 "height":8,
                 "id":1045,
                 "name":"",
                 "rotation":0,
                 "type":"",
                 "visible":true,
                 "width":8,
                 "x":2720,
                 "y":200
                }, 
                {
                 "gid":6280,
                 "height":8,
                 "id":1046,
                 "name":"",
                 "rotation":0,
                 "type":"",
                 "visible":true,
                 "width":16,
                 "x":2616,
                 "y":216
                }, 
                {
                 "height":80,
                 "id":1047,
                 "name":"",
                 "properties":
                    {
                     "parameters":"{\"locationType\":\"atprk_apexarea48.atprk_apexarea48takeoff\"}",
                     "stagehand":"questlocation"
                    },
                 "propertytypes":
                    {
                     "parameters":"string",
                     "stagehand":"string"
                    },
                 "rotation":0,
                 "type":"",
                 "visible":true,
                 "width":128,
                 "x":1976,
                 "y":200
                }, 
                {
                 "gid":2715,
                 "height":16,
                 "id":1048,
                 "name":"",
                 "rotation":0,
                 "type":"",
                 "visible":true,
                 "width":32,
                 "x":1672,
                 "y":232
                }, 
                {
                 "gid":2715,
                 "height":16,
                 "id":1049,
                 "name":"",
                 "rotation":0,
                 "type":"",
                 "visible":true,
                 "width":32,
                 "x":1736,
                 "y":232
                }, 
                {
                 "gid":2147491058,
                 "height":16,
                 "id":1051,
                 "name":"",
                 "properties":
                    {
                     "parameters":"{ \"treasurePools\" : [ \"atprk_apexarea48Treasure\" ] }"
                    },
                 "propertytypes":
                    {
                     "parameters":"string"
                    },
                 "rotation":0,
                 "type":"",
                 "visible":true,
                 "width":24,
                 "x":2160,
                 "y":280
                }, 
                {
                 "gid":7410,
                 "height":16,
                 "id":1052,
                 "name":"",
                 "properties":
                    {
                     "parameters":"{ \"treasurePools\" : [ \"atprk_apexarea48Treasure\" ] }"
                    },
                 "propertytypes":
                    {
                     "parameters":"string"
                    },
                 "rotation":0,
                 "type":"",
                 "visible":true,
                 "width":24,
                 "x":2160,
                 "y":264
                }, 
                {
                 "gid":2685,
                 "height":16,
                 "id":1053,
                 "name":"",
                 "rotation":0,
                 "type":"",
                 "visible":true,
                 "width":16,
                 "x":2144,
                 "y":280
                }, 
                {
                 "gid":8922,
                 "height":16,
                 "id":1063,
                 "name":"",
                 "rotation":0,
                 "type":"",
                 "visible":true,
                 "width":24,
                 "x":1296,
                 "y":280
                }],
         "opacity":1,
         "type":"objectgroup",
         "visible":true,
         "x":0,
         "y":0
        }, 
        {
         "color":"#ffff00",
         "draworder":"topdown",
         "name":"wiring - lights & guns",
         "objects":[
                {
                 "height":0,
                 "id":1024,
                 "name":"",
                 "polyline":[
                        {
                         "x":0,
                         "y":0
                        }, 
                        {
                         "x":8,
                         "y":-16
                        }],
                 "rotation":0,
                 "type":"",
                 "visible":true,
                 "width":0,
                 "x":1816,
                 "y":248
                }, 
                {
                 "height":0,
                 "id":1025,
                 "name":"",
                 "polyline":[
                        {
                         "x":0,
                         "y":0
                        }, 
                        {
                         "x":-8,
                         "y":-16
                        }],
                 "rotation":0,
                 "type":"",
                 "visible":true,
                 "width":0,
                 "x":1832,
                 "y":248
                }, 
                {
                 "height":0,
                 "id":1026,
                 "name":"",
                 "polyline":[
                        {
                         "x":0,
                         "y":0
                        }, 
                        {
                         "x":-8,
                         "y":-16
                        }],
                 "rotation":0,
                 "type":"",
                 "visible":true,
                 "width":0,
                 "x":1944,
                 "y":248
                }, 
                {
                 "height":0,
                 "id":1027,
                 "name":"",
                 "polyline":[
                        {
                         "x":0,
                         "y":0
                        }, 
                        {
                         "x":8,
                         "y":-16
                        }],
                 "rotation":0,
                 "type":"",
                 "visible":true,
                 "width":0,
                 "x":1928,
                 "y":248
                }],
         "opacity":1,
         "type":"objectgroup",
         "visible":true,
         "x":0,
         "y":0
        }, 
        {
         "color":"#ff0000",
         "draworder":"topdown",
         "name":"monsters & npcs",
         "objects":[
                {
                 "height":8,
                 "id":1011,
                 "name":"",
                 "properties":
                    {
                     "npc":"apex",
                     "typeName":"apexscout"
                    },
                 "propertytypes":
                    {
                     "npc":"string",
                     "typeName":"string"
                    },
                 "rotation":0,
                 "type":"",
                 "visible":true,
                 "width":8,
                 "x":1632,
                 "y":288
                }, 
                {
                 "height":8,
                 "id":1012,
                 "name":"",
                 "properties":
                    {
                     "npc":"apex",
                     "typeName":"labscientist"
                    },
                 "propertytypes":
                    {
                     "npc":"string",
                     "typeName":"string"
                    },
                 "rotation":0,
                 "type":"",
                 "visible":true,
                 "width":8,
                 "x":1320,
                 "y":176
                }, 
                {
                 "height":8,
                 "id":1013,
                 "name":"",
                 "properties":
                    {
                     "npc":"apex",
                     "typeName":"labscientist"
                    },
                 "propertytypes":
                    {
                     "npc":"string",
                     "typeName":"string"
                    },
                 "rotation":0,
                 "type":"",
                 "visible":true,
                 "width":8,
                 "x":1432,
                 "y":288
                }, 
                {
                 "height":8,
                 "id":1042,
                 "name":"",
                 "properties":
                    {
                     "npc":"apex",
                     "typeName":"atprk_apexufopilot"
                    },
                 "propertytypes":
                    {
                     "npc":"string",
                     "typeName":"string"
                    },
                 "rotation":0,
                 "type":"",
                 "visible":true,
                 "width":8,
                 "x":2624,
                 "y":160
                }, 
                {
                 "height":8,
                 "id":1050,
                 "name":"",
                 "properties":
                    {
                     "npc":"apex",
                     "typeName":"apexscout"
                    },
                 "propertytypes":
                    {
                     "npc":"string",
                     "typeName":"string"
                    },
                 "rotation":0,
                 "type":"",
                 "visible":true,
                 "width":8,
                 "x":2128,
                 "y":248
                }],
         "opacity":1,
         "type":"objectgroup",
         "visible":true,
         "x":0,
         "y":0
        }, 
        {
         "color":"#00ffff",
         "draworder":"topdown",
         "name":"wiring - locked door",
         "objects":[],
         "opacity":1,
         "type":"objectgroup",
         "visible":true,
         "x":0,
         "y":0
        }, 
        {
         "draworder":"topdown",
         "name":"outside the map",
         "objects":[],
         "opacity":1,
         "type":"objectgroup",
         "visible":true,
         "x":0,
         "y":0
        }, 
        {
         "draworder":"topdown",
         "name":"anchors etc",
         "objects":[
                {
                 "gid":248,
                 "height":8,
                 "id":1016,
                 "name":"",
                 "rotation":0,
                 "type":"",
                 "visible":true,
                 "width":8,
                 "x":1536,
                 "y":128
                }],
         "opacity":1,
         "type":"objectgroup",
         "visible":true,
         "x":0,
         "y":0
        }, 
        {
         "draworder":"topdown",
         "name":"items",
         "objects":[],
         "opacity":1,
         "type":"objectgroup",
         "visible":true,
         "x":0,
         "y":0
        }],
 "nextobjectid":1064,
 "orientation":"orthogonal",
 "renderorder":"right-down",
 "tiledversion":"1.1.1",
 "tileheight":8,
 "tilesets":[
        {
         "firstgid":1,
         "source":"..\/..\/..\/tilesets\/packed\/materials.json"
        }, 
        {
         "firstgid":198,
         "source":"..\/..\/..\/tilesets\/packed\/supports.json"
        }, 
        {
         "firstgid":235,
         "source":"..\/..\/..\/tilesets\/packed\/miscellaneous.json"
        }, 
        {
         "firstgid":259,
         "source":"..\/..\/..\/tilesets\/packed\/liquids.json"
        }, 
        {
         "firstgid":287,
         "source":"..\/..\/..\/tilesets\/packed\/objects-by-race\/generic.json"
        }, 
        {
         "firstgid":2271,
         "source":"..\/..\/..\/tilesets\/packed\/objects-by-race\/ancient.json"
        }, 
        {
         "firstgid":2434,
         "source":"..\/..\/..\/tilesets\/packed\/objects-by-race\/apex.json"
        }, 
        {
         "firstgid":2805,
         "source":"..\/..\/..\/tilesets\/packed\/objects-by-race\/avian.json"
        }, 
        {
         "firstgid":3110,
         "source":"..\/..\/..\/tilesets\/packed\/objects-by-race\/floran.json"
        }, 
        {
         "firstgid":3305,
         "source":"..\/..\/..\/tilesets\/packed\/objects-by-race\/glitch.json"
        }, 
        {
         "firstgid":3531,
         "source":"..\/..\/..\/tilesets\/packed\/objects-by-race\/human.json"
        }, 
        {
         "firstgid":3819,
         "source":"..\/..\/..\/tilesets\/packed\/objects-by-race\/hylotl.json"
        }, 
        {
         "firstgid":4051,
         "source":"..\/..\/..\/tilesets\/packed\/objects-by-race\/novakid.json"
        }, 
        {
         "firstgid":4115,
         "source":"..\/..\/..\/tilesets\/packed\/objects-by-category\/crafting.json"
        }, 
        {
         "firstgid":4195,
         "source":"..\/..\/..\/tilesets\/packed\/objects-by-category\/decorative.json"
        }, 
        {
         "firstgid":5636,
         "source":"..\/..\/..\/tilesets\/packed\/objects-by-category\/door.json"
        }, 
        {
         "firstgid":5768,
         "source":"..\/..\/..\/tilesets\/packed\/objects-by-category\/farmable.json"
        }, 
        {
         "firstgid":5843,
         "source":"..\/..\/..\/tilesets\/packed\/objects-by-category\/furniture.json"
        }, 
        {
         "firstgid":6197,
         "source":"..\/..\/..\/tilesets\/packed\/objects-by-category\/light.json"
        }, 
        {
         "firstgid":6655,
         "source":"..\/..\/..\/tilesets\/packed\/objects-by-category\/other.json"
        }, 
        {
         "firstgid":6967,
         "source":"..\/..\/..\/tilesets\/packed\/objects-by-category\/pot.json"
        }, 
        {
         "firstgid":7264,
         "source":"..\/..\/..\/tilesets\/packed\/objects-by-category\/sapling.json"
        }, 
        {
         "firstgid":7265,
         "source":"..\/..\/..\/tilesets\/packed\/objects-by-category\/spawner.json"
        }, 
        {
         "firstgid":7281,
         "source":"..\/..\/..\/tilesets\/packed\/objects-by-category\/storage.json"
        }, 
        {
         "firstgid":7515,
         "source":"..\/..\/..\/tilesets\/packed\/objects-by-category\/teleporter.json"
        }, 
        {
         "firstgid":7557,
         "source":"..\/..\/..\/tilesets\/packed\/objects-by-category\/tools.json"
        }, 
        {
         "firstgid":7562,
         "source":"..\/..\/..\/tilesets\/packed\/objects-by-category\/trap.json"
        }, 
        {
         "firstgid":7766,
         "source":"..\/..\/..\/tilesets\/packed\/objects-by-category\/wire.json"
        }, 
        {
         "firstgid":7988,
         "source":"..\/..\/..\/tilesets\/packed\/objects-by-type\/container.json"
        }, 
        {
         "firstgid":8273,
         "source":"..\/..\/..\/tilesets\/packed\/objects-by-type\/farmable.json"
        }, 
        {
         "firstgid":8351,
         "source":"..\/..\/..\/tilesets\/packed\/objects-by-type\/loungeable.json"
        }, 
        {
         "firstgid":8632,
         "source":"..\/..\/..\/tilesets\/packed\/objects-by-type\/noisy.json"
        }, 
        {
         "firstgid":8673,
         "source":"..\/..\/..\/tilesets\/packed\/objects-by-type\/teleporter.json"
        }, 
        {
         "firstgid":8700,
         "source":"..\/..\/..\/tilesets\/packed\/huge-objects.json"
        }, 
        {
         "firstgid":8801,
         "source":"..\/..\/..\/..\/..\/mods\/precursorracekrakoth\/tilesets\/precursorracekrakoth_custom\/atprk-krakothdungeonset2.json"
        }, 
        {
         "firstgid":8845,
         "source":"..\/..\/..\/..\/..\/mods\/precursorracekrakoth\/tilesets\/precursorracekrakoth_custom\/atprk-krakothdungeonset1.json"
        }],
 "tilewidth":8,
 "type":"map",
 "version":1,
 "width":400
}