{ "backgroundcolor":"#000000",
 "height":52,
 "infinite":false,
 "layers":[
        {
         "compression":"zlib",
         "data":"eJzl120KgzAMBuBey6Pt346hF5r\/PNM2UAihH0labd42EGQT6vNmLcM9hPc+UH9CCNbWlPUZd7h7NLKdZ2i5Jq2NfUbx\/90LsD+VYXR\/rCT+WIYWldpH1krZYzl4LYbe2JW2dF1uz\/13Hb\/7V1u8Gr+lqS9nR\/DTDPz7Efya5vU6r9TP76VK+szS\/qnJYPFLzTF7qywSv9Uucddm4FXya9a2vg\/UZMj5n7BbMkj82pkg+1u8U2oylPxPz77mNxjN38tu3UOo\/isD9fe2z+Y\/JvbfYbdkmNHvwT2rv5d9PRvV32L+T53Z1Ky9+9dMI\/gtGVD8KPPXngEv\/lQONL82i8RP9yGKP3Z+0OaP7h9l\/\/fySzJI\/T3sGr\/H2Uv99OrNrzkHHu2aDF7tNVl6Wz30F\/9CqAQ=",
         "encoding":"base64",
         "height":52,
         "name":"back",
         "opacity":0.5,
         "type":"tilelayer",
         "visible":true,
         "width":48,
         "x":0,
         "y":0
        }, 
        {
         "compression":"zlib",
         "data":"eJzt1VuOgzAMBVC2xdLYCd0Qn11IVzEzH4wiK4lf17GRaslqVRA5NwnptW3b9e3\/llS20ePP9nnmvbJfkiPbJrGPsmTbPGuR7ajsj3z+CnuvstdN673r3el90NfkmqUv5pnUxdkRY3q7N5+9DNx9ETZpboS\/7b9xD\/LZ9tH0aB8fgu\/SubdmmPlH17gsVrt3HTgP0s+VJgPCj5p7awbk+S4ZD+1HZZCOJa2VfrS9ol9b1fxRe8fr14wT5fdk0I4TYV\/p5zI8wT\/LUN0\/K6vd6q+yd6wZkHZEhgpnpyfDR9lRfmuGSn5Lhij\/Cjvnf\/32afCvskv8u9IfYadjS\/bJbX81v51gv2eOuSzUj7Zrcpyd5vJRf4X39rZza9DbO5K1zHh\/JX56Bo3W0buPrDkke6c1S\/4bvKXxt67WTue4twYR77M2Qzu31D+7N+p9tuSg59PIH3kOoTN4zoTVdqQ\/w04zPG3u0Y2up\/szcqwoqynbTWul5wc6F6yV",
         "encoding":"base64",
         "height":52,
         "name":"front",
         "opacity":1,
         "type":"tilelayer",
         "visible":true,
         "width":48,
         "x":0,
         "y":0
        }, 
        {
         "color":"#5555ff",
         "draworder":"topdown",
         "name":"mods",
         "objects":[],
         "opacity":1,
         "type":"objectgroup",
         "visible":true,
         "x":0,
         "y":0
        }, 
        {
         "color":"#ff0000",
         "draworder":"topdown",
         "name":"objects",
         "objects":[
                {
                 "gid":3477,
                 "height":16,
                 "id":807,
                 "name":"",
                 "properties":
                    {
                     "parameters":"{\"treasurePools\":[\"atprk_forgottenmountainsChestTreasure\"]}"
                    },
                 "propertytypes":
                    {
                     "parameters":"string"
                    },
                 "rotation":0,
                 "type":"",
                 "visible":true,
                 "width":16,
                 "x":96,
                 "y":296
                }, 
                {
                 "height":64,
                 "id":809,
                 "name":"",
                 "properties":
                    {
                     "parameters":"{\"locationType\":\"atprk_forgottenmountains.atprk_forgottenbridge1\"}",
                     "stagehand":"questlocation"
                    },
                 "propertytypes":
                    {
                     "parameters":"string",
                     "stagehand":"string"
                    },
                 "rotation":0,
                 "type":"",
                 "visible":true,
                 "width":112,
                 "x":56,
                 "y":16
                }, 
                {
                 "height":64,
                 "id":810,
                 "name":"",
                 "properties":
                    {
                     "parameters":"{\"locationType\":\"atprk_forgottenmountains.atprk_forgottenbridge1\"}",
                     "stagehand":"questlocation"
                    },
                 "propertytypes":
                    {
                     "parameters":"string",
                     "stagehand":"string"
                    },
                 "rotation":0,
                 "type":"",
                 "visible":true,
                 "width":112,
                 "x":216,
                 "y":16
                }],
         "opacity":1,
         "type":"objectgroup",
         "visible":true,
         "x":0,
         "y":0
        }, 
        {
         "color":"#ffff00",
         "draworder":"topdown",
         "name":"wiring - lights & guns",
         "objects":[],
         "opacity":1,
         "type":"objectgroup",
         "visible":true,
         "x":0,
         "y":0
        }, 
        {
         "color":"#ff0000",
         "draworder":"topdown",
         "name":"monsters & npcs",
         "objects":[],
         "opacity":1,
         "type":"objectgroup",
         "visible":true,
         "x":0,
         "y":0
        }, 
        {
         "color":"#00ffff",
         "draworder":"topdown",
         "name":"wiring - locked door",
         "objects":[],
         "opacity":1,
         "type":"objectgroup",
         "visible":true,
         "x":0,
         "y":0
        }, 
        {
         "draworder":"topdown",
         "name":"outside the map",
         "objects":[],
         "opacity":1,
         "type":"objectgroup",
         "visible":true,
         "x":0,
         "y":0
        }, 
        {
         "draworder":"topdown",
         "name":"anchors etc",
         "objects":[
                {
                 "gid":203,
                 "height":8,
                 "id":785,
                 "name":"",
                 "rotation":0,
                 "type":"",
                 "visible":true,
                 "width":8,
                 "x":352,
                 "y":112
                }, 
                {
                 "gid":203,
                 "height":8,
                 "id":786,
                 "name":"",
                 "rotation":0,
                 "type":"",
                 "visible":true,
                 "width":8,
                 "x":32,
                 "y":112
                }, 
                {
                 "gid":203,
                 "height":8,
                 "id":787,
                 "name":"",
                 "rotation":0,
                 "type":"",
                 "visible":true,
                 "width":8,
                 "x":272,
                 "y":232
                }, 
                {
                 "gid":203,
                 "height":8,
                 "id":788,
                 "name":"",
                 "rotation":0,
                 "type":"",
                 "visible":true,
                 "width":8,
                 "x":184,
                 "y":408
                }, 
                {
                 "gid":203,
                 "height":8,
                 "id":789,
                 "name":"",
                 "rotation":0,
                 "type":"",
                 "visible":true,
                 "width":8,
                 "x":104,
                 "y":232
                }, 
                {
                 "gid":202,
                 "height":8,
                 "id":790,
                 "name":"",
                 "rotation":0,
                 "type":"",
                 "visible":true,
                 "width":8,
                 "x":368,
                 "y":48
                }, 
                {
                 "gid":202,
                 "height":8,
                 "id":791,
                 "name":"",
                 "rotation":0,
                 "type":"",
                 "visible":true,
                 "width":8,
                 "x":344,
                 "y":80
                }, 
                {
                 "gid":202,
                 "height":8,
                 "id":792,
                 "name":"",
                 "rotation":0,
                 "type":"",
                 "visible":true,
                 "width":8,
                 "x":344,
                 "y":16
                }, 
                {
                 "gid":202,
                 "height":8,
                 "id":793,
                 "name":"",
                 "rotation":0,
                 "type":"",
                 "visible":true,
                 "width":8,
                 "x":184,
                 "y":16
                }, 
                {
                 "gid":202,
                 "height":8,
                 "id":794,
                 "name":"",
                 "rotation":0,
                 "type":"",
                 "visible":true,
                 "width":8,
                 "x":32,
                 "y":16
                }, 
                {
                 "gid":202,
                 "height":8,
                 "id":795,
                 "name":"",
                 "rotation":0,
                 "type":"",
                 "visible":true,
                 "width":8,
                 "x":32,
                 "y":80
                }, 
                {
                 "gid":202,
                 "height":8,
                 "id":796,
                 "name":"",
                 "rotation":0,
                 "type":"",
                 "visible":true,
                 "width":8,
                 "x":8,
                 "y":48
                }, 
                {
                 "gid":214,
                 "height":8,
                 "id":797,
                 "name":"",
                 "rotation":0,
                 "type":"",
                 "visible":true,
                 "width":8,
                 "x":344,
                 "y":80
                }, 
                {
                 "gid":214,
                 "height":8,
                 "id":798,
                 "name":"",
                 "rotation":0,
                 "type":"",
                 "visible":true,
                 "width":8,
                 "x":368,
                 "y":48
                }, 
                {
                 "gid":214,
                 "height":8,
                 "id":799,
                 "name":"",
                 "rotation":0,
                 "type":"",
                 "visible":true,
                 "width":8,
                 "x":344,
                 "y":16
                }, 
                {
                 "gid":214,
                 "height":8,
                 "id":800,
                 "name":"",
                 "rotation":0,
                 "type":"",
                 "visible":true,
                 "width":8,
                 "x":184,
                 "y":16
                }, 
                {
                 "gid":214,
                 "height":8,
                 "id":801,
                 "name":"",
                 "rotation":0,
                 "type":"",
                 "visible":true,
                 "width":8,
                 "x":32,
                 "y":16
                }, 
                {
                 "gid":214,
                 "height":8,
                 "id":802,
                 "name":"",
                 "rotation":0,
                 "type":"",
                 "visible":true,
                 "width":8,
                 "x":8,
                 "y":48
                }, 
                {
                 "gid":214,
                 "height":8,
                 "id":803,
                 "name":"",
                 "rotation":0,
                 "type":"",
                 "visible":true,
                 "width":8,
                 "x":32,
                 "y":80
                }],
         "opacity":1,
         "type":"objectgroup",
         "visible":true,
         "x":0,
         "y":0
        }, 
        {
         "draworder":"topdown",
         "name":"items",
         "objects":[],
         "opacity":1,
         "type":"objectgroup",
         "visible":true,
         "x":0,
         "y":0
        }],
 "nextobjectid":811,
 "orientation":"orthogonal",
 "renderorder":"right-down",
 "tiledversion":"1.1.1",
 "tileheight":8,
 "tilesets":[
        {
         "firstgid":1,
         "source":"..\/..\/..\/..\/tilesets\/packed\/materials.json"
        }, 
        {
         "firstgid":198,
         "source":"..\/..\/..\/..\/tilesets\/packed\/miscellaneous.json"
        }, 
        {
         "firstgid":222,
         "source":"..\/..\/..\/..\/tilesets\/packed\/liquids.json"
        }, 
        {
         "firstgid":250,
         "source":"..\/..\/..\/..\/tilesets\/packed\/supports.json"
        }, 
        {
         "firstgid":287,
         "source":"..\/..\/..\/..\/tilesets\/packed\/objects-by-race\/generic.json"
        }, 
        {
         "firstgid":2271,
         "source":"..\/..\/..\/..\/tilesets\/packed\/objects-by-race\/ancient.json"
        }, 
        {
         "firstgid":2434,
         "source":"..\/..\/..\/..\/tilesets\/packed\/objects-by-race\/apex.json"
        }, 
        {
         "firstgid":2805,
         "source":"..\/..\/..\/..\/tilesets\/packed\/objects-by-race\/avian.json"
        }, 
        {
         "firstgid":3110,
         "source":"..\/..\/..\/..\/tilesets\/packed\/objects-by-race\/floran.json"
        }, 
        {
         "firstgid":3305,
         "source":"..\/..\/..\/..\/tilesets\/packed\/objects-by-race\/glitch.json"
        }, 
        {
         "firstgid":3531,
         "source":"..\/..\/..\/..\/tilesets\/packed\/objects-by-race\/human.json"
        }, 
        {
         "firstgid":3819,
         "source":"..\/..\/..\/..\/tilesets\/packed\/objects-by-race\/hylotl.json"
        }, 
        {
         "firstgid":4051,
         "source":"..\/..\/..\/..\/tilesets\/packed\/objects-by-race\/novakid.json"
        }, 
        {
         "firstgid":4115,
         "source":"..\/..\/..\/..\/tilesets\/packed\/objects-by-category\/crafting.json"
        }, 
        {
         "firstgid":4195,
         "source":"..\/..\/..\/..\/tilesets\/packed\/objects-by-category\/decorative.json"
        }, 
        {
         "firstgid":5636,
         "source":"..\/..\/..\/..\/tilesets\/packed\/objects-by-category\/door.json"
        }, 
        {
         "firstgid":5768,
         "source":"..\/..\/..\/..\/tilesets\/packed\/objects-by-category\/farmable.json"
        }, 
        {
         "firstgid":5843,
         "source":"..\/..\/..\/..\/tilesets\/packed\/objects-by-category\/furniture.json"
        }, 
        {
         "firstgid":6197,
         "source":"..\/..\/..\/..\/tilesets\/packed\/objects-by-category\/light.json"
        }, 
        {
         "firstgid":6655,
         "source":"..\/..\/..\/..\/tilesets\/packed\/objects-by-category\/other.json"
        }, 
        {
         "firstgid":6967,
         "source":"..\/..\/..\/..\/tilesets\/packed\/objects-by-category\/pot.json"
        }, 
        {
         "firstgid":7264,
         "source":"..\/..\/..\/..\/tilesets\/packed\/objects-by-category\/sapling.json"
        }, 
        {
         "firstgid":7265,
         "source":"..\/..\/..\/..\/tilesets\/packed\/objects-by-category\/spawner.json"
        }, 
        {
         "firstgid":7281,
         "source":"..\/..\/..\/..\/tilesets\/packed\/objects-by-category\/storage.json"
        }, 
        {
         "firstgid":7515,
         "source":"..\/..\/..\/..\/tilesets\/packed\/objects-by-category\/teleporter.json"
        }, 
        {
         "firstgid":7557,
         "source":"..\/..\/..\/..\/tilesets\/packed\/objects-by-category\/tools.json"
        }, 
        {
         "firstgid":7562,
         "source":"..\/..\/..\/..\/tilesets\/packed\/objects-by-category\/trap.json"
        }, 
        {
         "firstgid":7766,
         "source":"..\/..\/..\/..\/tilesets\/packed\/objects-by-category\/wire.json"
        }, 
        {
         "firstgid":7988,
         "source":"..\/..\/..\/..\/tilesets\/packed\/objects-by-type\/container.json"
        }, 
        {
         "firstgid":8273,
         "source":"..\/..\/..\/..\/tilesets\/packed\/objects-by-type\/farmable.json"
        }, 
        {
         "firstgid":8351,
         "source":"..\/..\/..\/..\/tilesets\/packed\/objects-by-type\/loungeable.json"
        }, 
        {
         "firstgid":8632,
         "source":"..\/..\/..\/..\/tilesets\/packed\/objects-by-type\/noisy.json"
        }, 
        {
         "firstgid":8673,
         "source":"..\/..\/..\/..\/tilesets\/packed\/objects-by-type\/teleporter.json"
        }, 
        {
         "firstgid":8700,
         "source":"..\/..\/..\/..\/tilesets\/packed\/huge-objects.json"
        }],
 "tilewidth":8,
 "type":"map",
 "version":1,
 "width":48
}