{ "backgroundcolor":"#000000",
 "height":68,
 "infinite":false,
 "layers":[
        {
         "compression":"zlib",
         "data":"eJzt2EuOwyAMANAcvescbLrrmWaohBR5MDb4B8KW2DRx4leoafK+rtc7x79xLR4nGLE4xQnjJGuNk6w10iu3\/hgNrdD0jtYb4bf2zuR4eQWX+YbFOrRY3zv0qdO8JdI7F9bez9+4BaPkW6xnzZ5V46M4VtuPsHjOlSRvRS9nfjnRy9P0av\/nqLXe15z3mSedX4\/nBdirRry9njUTHs+Eq3i9nvk1vSVmvJ7vdbS9JbjeiHd3Ft5eaBjrmNlbNPsz5\/w6LKwcu8X+S50nNY\/85\/P0UrV4eGFdVuuZU4f1esbqsuhX6U1vetNr4a21t473vL281b0aY1cvJ3b1ltB6f7WD97T5rZ\/BvkPlY3k7eOG+cjc+p45zvkdNL2XuzYOV93kswkvVpemFx6K8sJemV+5t5UR6n2bs9031OywP+46ivdWMeajg3mMlL1aLprdXU6QX268oL7yG19xSXqr\/YH0WRi9vVy+2FkbzLNcyx4vVlF65l6ojvTZerC6qz2JrtZXHqcHTS9U24uVeM9oL50bLy713hJf7G0+v\/B7pjfNy3Ct4rdyaQ9O5utvSuprbyxpt9nZKzNy81nmRzlE\/9\/zo+iXm6DpOH7\/wLF6V",
         "encoding":"base64",
         "height":68,
         "name":"back",
         "opacity":0.5,
         "type":"tilelayer",
         "visible":true,
         "width":60,
         "x":0,
         "y":0
        }, 
        {
         "compression":"zlib",
         "data":"eJzt2MsOwiAQhWGe3wdz2WfSDQmS0sBczoxw\/oSdwflSbdFSGGOMMcbGvaMHAEfv3tG7d9m913e9FOvq9svsvQxXLbPXI3r3jl7GGPvt7tmfKcv5Zs8+EVnPtHLWi4he\/UxZzV7zrP6GQeQ5SyZnH72+3pdyb231PxB65Wm89TVW\/1\/1ob1Pe8\/e1zX3ft6v\/L1RZq95tJ85jzxnyeRsG92rLGbK+Eyil15pT9YIb3seOcnrcb4qgz1bL9p8kvfujH2y1yJ6Y7yj34wRXoQZ8d0tg33p9TdHe5HmGSvCi\/pcZ\/Zau2etKK+necWK9D6ZJe6ZZ220d8YtXbPvHeG1dK++p2Vod5SzT+r2WqiinUhr7RRnm3RWyesytnpNMl07af88+059AE98reU=",
         "encoding":"base64",
         "height":68,
         "name":"front",
         "opacity":1,
         "type":"tilelayer",
         "visible":true,
         "width":60,
         "x":0,
         "y":0
        }, 
        {
         "color":"#5555ff",
         "draworder":"topdown",
         "name":"mods",
         "objects":[],
         "opacity":1,
         "type":"objectgroup",
         "visible":true,
         "x":0,
         "y":0
        }, 
        {
         "color":"#ff0000",
         "draworder":"topdown",
         "name":"objects",
         "objects":[
                {
                 "gid":8809,
                 "height":40,
                 "id":888,
                 "name":"",
                 "properties":
                    {
                     "parameters":"{\"treasurePools\":[\"atprk_glaciovolcanicChestTreasure\"]}"
                    },
                 "propertytypes":
                    {
                     "parameters":"string"
                    },
                 "rotation":0,
                 "type":"",
                 "visible":true,
                 "width":24,
                 "x":240,
                 "y":272
                }, 
                {
                 "gid":8809,
                 "height":40,
                 "id":889,
                 "name":"",
                 "properties":
                    {
                     "parameters":"{\"treasurePools\":[\"atprk_glaciovolcanicChestTreasure\"]}"
                    },
                 "propertytypes":
                    {
                     "parameters":"string"
                    },
                 "rotation":0,
                 "type":"",
                 "visible":true,
                 "width":24,
                 "x":216,
                 "y":464
                }, 
                {
                 "gid":2147492457,
                 "height":40,
                 "id":890,
                 "name":"",
                 "properties":
                    {
                     "parameters":"{\"treasurePools\":[\"atprk_glaciovolcanicChestTreasure\"]}"
                    },
                 "propertytypes":
                    {
                     "parameters":"string"
                    },
                 "rotation":0,
                 "type":"",
                 "visible":true,
                 "width":24,
                 "x":264,
                 "y":464
                }, 
                {
                 "gid":8812,
                 "height":40,
                 "id":891,
                 "name":"",
                 "rotation":0,
                 "type":"",
                 "visible":true,
                 "width":40,
                 "x":232,
                 "y":352
                }, 
                {
                 "gid":8803,
                 "height":16,
                 "id":892,
                 "name":"",
                 "rotation":0,
                 "type":"",
                 "visible":true,
                 "width":22,
                 "x":280,
                 "y":112
                }, 
                {
                 "gid":8804,
                 "height":16,
                 "id":895,
                 "name":"",
                 "rotation":0,
                 "type":"",
                 "visible":true,
                 "width":22,
                 "x":200,
                 "y":112
                }, 
                {
                 "gid":8802,
                 "height":16,
                 "id":896,
                 "name":"",
                 "rotation":0,
                 "type":"",
                 "visible":true,
                 "width":22,
                 "x":256,
                 "y":112
                }, 
                {
                 "gid":8801,
                 "height":16,
                 "id":897,
                 "name":"",
                 "rotation":0,
                 "type":"",
                 "visible":true,
                 "width":22,
                 "x":224,
                 "y":112
                }, 
                {
                 "gid":8813,
                 "height":40,
                 "id":898,
                 "name":"",
                 "rotation":0,
                 "type":"",
                 "visible":true,
                 "width":24,
                 "x":192,
                 "y":272
                }, 
                {
                 "gid":2147492461,
                 "height":40,
                 "id":899,
                 "name":"",
                 "rotation":0,
                 "type":"",
                 "visible":true,
                 "width":24,
                 "x":288,
                 "y":272
                }, 
                {
                 "height":128,
                 "id":900,
                 "name":"",
                 "properties":
                    {
                     "parameters":"{\"locationType\":\"atprk_glaciovolcanic.atprk_noolithlibrary\"}",
                     "stagehand":"questlocation"
                    },
                 "propertytypes":
                    {
                     "parameters":"string",
                     "stagehand":"string"
                    },
                 "rotation":0,
                 "type":"",
                 "visible":true,
                 "width":152,
                 "x":176,
                 "y":152
                }, 
                {
                 "height":88,
                 "id":901,
                 "name":"",
                 "properties":
                    {
                     "parameters":"{\"locationType\":\"atprk_glaciovolcanic.atprk_noolithlibrary\"}",
                     "stagehand":"questlocation"
                    },
                 "propertytypes":
                    {
                     "parameters":"string",
                     "stagehand":"string"
                    },
                 "rotation":0,
                 "type":"",
                 "visible":true,
                 "width":128,
                 "x":192,
                 "y":376
                }],
         "opacity":1,
         "type":"objectgroup",
         "visible":true,
         "x":0,
         "y":0
        }, 
        {
         "color":"#ffff00",
         "draworder":"topdown",
         "name":"wiring - lights & guns",
         "objects":[],
         "opacity":1,
         "type":"objectgroup",
         "visible":true,
         "x":0,
         "y":0
        }, 
        {
         "color":"#ff0000",
         "draworder":"topdown",
         "name":"monsters & npcs",
         "objects":[],
         "opacity":1,
         "type":"objectgroup",
         "visible":true,
         "x":0,
         "y":0
        }, 
        {
         "color":"#00ffff",
         "draworder":"topdown",
         "name":"wiring - locked door",
         "objects":[],
         "opacity":1,
         "type":"objectgroup",
         "visible":true,
         "x":0,
         "y":0
        }, 
        {
         "draworder":"topdown",
         "name":"outside the map",
         "objects":[],
         "opacity":1,
         "type":"objectgroup",
         "visible":true,
         "x":0,
         "y":0
        }, 
        {
         "draworder":"topdown",
         "name":"anchors etc",
         "objects":[
                {
                 "gid":202,
                 "height":8,
                 "id":708,
                 "name":"",
                 "rotation":0,
                 "type":"",
                 "visible":true,
                 "width":8,
                 "x":392,
                 "y":24
                }, 
                {
                 "gid":202,
                 "height":8,
                 "id":709,
                 "name":"",
                 "rotation":0,
                 "type":"",
                 "visible":true,
                 "width":8,
                 "x":240,
                 "y":24
                }, 
                {
                 "gid":202,
                 "height":8,
                 "id":710,
                 "name":"",
                 "rotation":0,
                 "type":"",
                 "visible":true,
                 "width":8,
                 "x":80,
                 "y":24
                }, 
                {
                 "gid":202,
                 "height":8,
                 "id":711,
                 "name":"",
                 "rotation":0,
                 "type":"",
                 "visible":true,
                 "width":8,
                 "x":80,
                 "y":192
                }, 
                {
                 "gid":202,
                 "height":8,
                 "id":712,
                 "name":"",
                 "rotation":0,
                 "type":"",
                 "visible":true,
                 "width":8,
                 "x":392,
                 "y":192
                }, 
                {
                 "gid":203,
                 "height":8,
                 "id":713,
                 "name":"",
                 "rotation":0,
                 "type":"",
                 "visible":true,
                 "width":8,
                 "x":400,
                 "y":224
                }, 
                {
                 "gid":203,
                 "height":8,
                 "id":714,
                 "name":"",
                 "rotation":0,
                 "type":"",
                 "visible":true,
                 "width":8,
                 "x":72,
                 "y":224
                }, 
                {
                 "gid":202,
                 "height":8,
                 "id":715,
                 "name":"",
                 "rotation":0,
                 "type":"",
                 "visible":true,
                 "width":8,
                 "x":392,
                 "y":104
                }, 
                {
                 "gid":202,
                 "height":8,
                 "id":716,
                 "name":"",
                 "rotation":0,
                 "type":"",
                 "visible":true,
                 "width":8,
                 "x":80,
                 "y":104
                }, 
                {
                 "gid":203,
                 "height":8,
                 "id":881,
                 "name":"",
                 "rotation":0,
                 "type":"",
                 "visible":true,
                 "width":8,
                 "x":360,
                 "y":488
                }, 
                {
                 "gid":203,
                 "height":8,
                 "id":882,
                 "name":"",
                 "rotation":0,
                 "type":"",
                 "visible":true,
                 "width":8,
                 "x":392,
                 "y":360
                }, 
                {
                 "gid":203,
                 "height":8,
                 "id":883,
                 "name":"",
                 "rotation":0,
                 "type":"",
                 "visible":true,
                 "width":8,
                 "x":88,
                 "y":360
                }, 
                {
                 "gid":203,
                 "height":8,
                 "id":884,
                 "name":"",
                 "rotation":0,
                 "type":"",
                 "visible":true,
                 "width":8,
                 "x":128,
                 "y":488
                }],
         "opacity":1,
         "type":"objectgroup",
         "visible":true,
         "x":0,
         "y":0
        }, 
        {
         "draworder":"topdown",
         "name":"items",
         "objects":[],
         "opacity":1,
         "type":"objectgroup",
         "visible":true,
         "x":0,
         "y":0
        }],
 "nextobjectid":902,
 "orientation":"orthogonal",
 "renderorder":"right-down",
 "tiledversion":"1.1.1",
 "tileheight":8,
 "tilesets":[
        {
         "firstgid":1,
         "source":"..\/..\/..\/..\/tilesets\/packed\/materials.json"
        }, 
        {
         "firstgid":198,
         "source":"..\/..\/..\/..\/tilesets\/packed\/miscellaneous.json"
        }, 
        {
         "firstgid":222,
         "source":"..\/..\/..\/..\/tilesets\/packed\/liquids.json"
        }, 
        {
         "firstgid":250,
         "source":"..\/..\/..\/..\/tilesets\/packed\/supports.json"
        }, 
        {
         "firstgid":287,
         "source":"..\/..\/..\/..\/tilesets\/packed\/objects-by-race\/generic.json"
        }, 
        {
         "firstgid":2271,
         "source":"..\/..\/..\/..\/tilesets\/packed\/objects-by-race\/ancient.json"
        }, 
        {
         "firstgid":2434,
         "source":"..\/..\/..\/..\/tilesets\/packed\/objects-by-race\/apex.json"
        }, 
        {
         "firstgid":2805,
         "source":"..\/..\/..\/..\/tilesets\/packed\/objects-by-race\/avian.json"
        }, 
        {
         "firstgid":3110,
         "source":"..\/..\/..\/..\/tilesets\/packed\/objects-by-race\/floran.json"
        }, 
        {
         "firstgid":3305,
         "source":"..\/..\/..\/..\/tilesets\/packed\/objects-by-race\/glitch.json"
        }, 
        {
         "firstgid":3531,
         "source":"..\/..\/..\/..\/tilesets\/packed\/objects-by-race\/human.json"
        }, 
        {
         "firstgid":3819,
         "source":"..\/..\/..\/..\/tilesets\/packed\/objects-by-race\/hylotl.json"
        }, 
        {
         "firstgid":4051,
         "source":"..\/..\/..\/..\/tilesets\/packed\/objects-by-race\/novakid.json"
        }, 
        {
         "firstgid":4115,
         "source":"..\/..\/..\/..\/tilesets\/packed\/objects-by-category\/crafting.json"
        }, 
        {
         "firstgid":4195,
         "source":"..\/..\/..\/..\/tilesets\/packed\/objects-by-category\/decorative.json"
        }, 
        {
         "firstgid":5636,
         "source":"..\/..\/..\/..\/tilesets\/packed\/objects-by-category\/door.json"
        }, 
        {
         "firstgid":5768,
         "source":"..\/..\/..\/..\/tilesets\/packed\/objects-by-category\/farmable.json"
        }, 
        {
         "firstgid":5843,
         "source":"..\/..\/..\/..\/tilesets\/packed\/objects-by-category\/furniture.json"
        }, 
        {
         "firstgid":6197,
         "source":"..\/..\/..\/..\/tilesets\/packed\/objects-by-category\/light.json"
        }, 
        {
         "firstgid":6655,
         "source":"..\/..\/..\/..\/tilesets\/packed\/objects-by-category\/other.json"
        }, 
        {
         "firstgid":6967,
         "source":"..\/..\/..\/..\/tilesets\/packed\/objects-by-category\/pot.json"
        }, 
        {
         "firstgid":7264,
         "source":"..\/..\/..\/..\/tilesets\/packed\/objects-by-category\/sapling.json"
        }, 
        {
         "firstgid":7265,
         "source":"..\/..\/..\/..\/tilesets\/packed\/objects-by-category\/spawner.json"
        }, 
        {
         "firstgid":7281,
         "source":"..\/..\/..\/..\/tilesets\/packed\/objects-by-category\/storage.json"
        }, 
        {
         "firstgid":7515,
         "source":"..\/..\/..\/..\/tilesets\/packed\/objects-by-category\/teleporter.json"
        }, 
        {
         "firstgid":7557,
         "source":"..\/..\/..\/..\/tilesets\/packed\/objects-by-category\/tools.json"
        }, 
        {
         "firstgid":7562,
         "source":"..\/..\/..\/..\/tilesets\/packed\/objects-by-category\/trap.json"
        }, 
        {
         "firstgid":7766,
         "source":"..\/..\/..\/..\/tilesets\/packed\/objects-by-category\/wire.json"
        }, 
        {
         "firstgid":7988,
         "source":"..\/..\/..\/..\/tilesets\/packed\/objects-by-type\/container.json"
        }, 
        {
         "firstgid":8273,
         "source":"..\/..\/..\/..\/tilesets\/packed\/objects-by-type\/farmable.json"
        }, 
        {
         "firstgid":8351,
         "source":"..\/..\/..\/..\/tilesets\/packed\/objects-by-type\/loungeable.json"
        }, 
        {
         "firstgid":8632,
         "source":"..\/..\/..\/..\/tilesets\/packed\/objects-by-type\/noisy.json"
        }, 
        {
         "firstgid":8673,
         "source":"..\/..\/..\/..\/tilesets\/packed\/objects-by-type\/teleporter.json"
        }, 
        {
         "firstgid":8700,
         "source":"..\/..\/..\/..\/tilesets\/packed\/huge-objects.json"
        }, 
        {
         "firstgid":8801,
         "source":"..\/..\/..\/..\/..\/..\/mods\/precursorracekrakoth\/tilesets\/precursorracekrakoth_custom\/atprk-glaciovolcanicset1.json"
        }],
 "tilewidth":8,
 "type":"map",
 "version":1,
 "width":60
}