{ "backgroundcolor":"#000000",
 "height":40,
 "infinite":false,
 "layers":[
        {
         "compression":"zlib",
         "data":"eJztmMENgzAMRTMLq\/XCAAxQiUU6AZNx6wIVapGiiIAN\/olJ\/+FJqEXEfvwkwBzCc87wDiF4I1crCkQtnvpD33PEda\/2Utux17nl1VULtOR5iuqdnNVeItNLz+OP5XgAkY5T263W8xXX\/a\/nV\/clPrYmHad35NvCc66XuNc4Z48OQzrOnmfkvJLOPYTnOGdbjlY\/4859ODpHk2fkvJLOPW2mLfJs5VmTZ9S8ks69M57XnoakRw95ztV2Z89pljysz7napGvpqODq+ozOs5VnTZ69es65vmuepdddr7m3rx2teZp144pnD3m+k+ct15J1w0Oez+6DHj1L8lz6fTBXm\/S6Gs8Wz89WeS71fcN6H5R4Ru+De7\/H\/+fOtWBrHIv3wdJ5Rvmpweq5xvr8j5695bm2F4Rnb9\/rjmqWflsl+r2Pnss6pucyjum5jGN6xvulZ5xTS8+t30PrZ9EaYyLx4lVSV21XLUKvhBBCCCGEEA98AOXxDb8=",
         "encoding":"base64",
         "height":40,
         "name":"back",
         "opacity":0.5,
         "type":"tilelayer",
         "visible":true,
         "width":90,
         "x":0,
         "y":0
        }, 
        {
         "compression":"zlib",
         "data":"eJzt2bENwjAQBVBTsAibsQMbULEMU7ANJQugFFEsK86d7dj\/fPpf+gWFw\/lBkHBCyOdnsKPTY5aja95v2Pb6zBDfAavGPa0R9xzaceaWeGuu9wxji\/Zrsa51Xvb9HdyZrWucEcZa69H3mHS\/Sda5dUhjyRo9295ckvPeOvQ+jvZkZbZ0Lul3el3zjmplL5Znq3Fm6dzaT0HPdE6t0Q509lGNIZ3pPEvpTGdPRTmnWf+zp\/8FLDU3W4nz9bL1FbYur0ucc+cckjP6rKulGuvYOfaNq3U+OtuSzjfQVr2tV8OcsdZZOj\/07ixZPwpaaxw754J+rtbS1Lrl+Yx2vTSTR+fUundrfL04j7JuMfbi3Nu61diT8+iWBj2v9Z6Vnu+PNrLgW2IxU6y4auZizg9dGYZhGIZhGIaxkD8ot29m",
         "encoding":"base64",
         "height":40,
         "name":"front",
         "opacity":1,
         "type":"tilelayer",
         "visible":true,
         "width":90,
         "x":0,
         "y":0
        }, 
        {
         "color":"#5555ff",
         "draworder":"topdown",
         "name":"mods",
         "objects":[],
         "opacity":1,
         "type":"objectgroup",
         "visible":true,
         "x":0,
         "y":0
        }, 
        {
         "color":"#ff0000",
         "draworder":"topdown",
         "name":"objects",
         "objects":[
                {
                 "gid":8806,
                 "height":64,
                 "id":901,
                 "name":"",
                 "rotation":0,
                 "type":"",
                 "visible":true,
                 "width":24,
                 "x":40,
                 "y":144
                }, 
                {
                 "gid":8828,
                 "height":24,
                 "id":902,
                 "name":"",
                 "rotation":0,
                 "type":"",
                 "visible":true,
                 "width":24,
                 "x":160,
                 "y":88
                }, 
                {
                 "gid":8828,
                 "height":24,
                 "id":903,
                 "name":"",
                 "rotation":0,
                 "type":"",
                 "visible":true,
                 "width":24,
                 "x":232,
                 "y":88
                }, 
                {
                 "gid":8833,
                 "height":16,
                 "id":904,
                 "name":"",
                 "rotation":0,
                 "type":"",
                 "visible":true,
                 "width":16,
                 "x":136,
                 "y":88
                }, 
                {
                 "gid":2147492482,
                 "height":24,
                 "id":907,
                 "name":"",
                 "rotation":0,
                 "type":"",
                 "visible":true,
                 "width":32,
                 "x":256,
                 "y":112
                }, 
                {
                 "gid":8812,
                 "height":24,
                 "id":909,
                 "name":"",
                 "properties":
                    {
                     "parameters":"{ \"treasurePools\" : [ \"atprk_krakothlabTreasure\" ] }"
                    },
                 "propertytypes":
                    {
                     "parameters":"string"
                    },
                 "rotation":0,
                 "type":"",
                 "visible":true,
                 "width":32,
                 "x":192,
                 "y":112
                }, 
                {
                 "gid":8806,
                 "height":64,
                 "id":910,
                 "name":"",
                 "rotation":0,
                 "type":"",
                 "visible":true,
                 "width":24,
                 "x":352,
                 "y":144
                }, 
                {
                 "gid":8833,
                 "height":16,
                 "id":916,
                 "name":"",
                 "rotation":0,
                 "type":"",
                 "visible":true,
                 "width":16,
                 "x":432,
                 "y":104
                }, 
                {
                 "height":8,
                 "id":919,
                 "name":"",
                 "properties":
                    {
                     "monster":"atprk_krakothsmalldrone"
                    },
                 "propertytypes":
                    {
                     "monster":"string"
                    },
                 "rotation":0,
                 "type":"",
                 "visible":true,
                 "width":8,
                 "x":208,
                 "y":72
                }, 
                {
                 "gid":8833,
                 "height":16,
                 "id":921,
                 "name":"",
                 "rotation":0,
                 "type":"",
                 "visible":true,
                 "width":16,
                 "x":584,
                 "y":104
                }, 
                {
                 "gid":2147490688,
                 "height":16,
                 "id":922,
                 "name":"",
                 "rotation":0,
                 "type":"",
                 "visible":true,
                 "width":24,
                 "x":512,
                 "y":144
                }, 
                {
                 "gid":7196,
                 "height":16,
                 "id":925,
                 "name":"",
                 "rotation":0,
                 "type":"",
                 "visible":true,
                 "width":16,
                 "x":496,
                 "y":152
                }, 
                {
                 "gid":8835,
                 "height":24,
                 "id":926,
                 "name":"",
                 "rotation":0,
                 "type":"",
                 "visible":true,
                 "width":32,
                 "x":128,
                 "y":112
                }, 
                {
                 "gid":8867,
                 "height":24,
                 "id":929,
                 "name":"",
                 "properties":
                    {
                     "parameters":"{ \"treasurePools\" : [ \"atprk_krakothlabTreasure\" ] }"
                    },
                 "propertytypes":
                    {
                     "parameters":"string"
                    },
                 "rotation":0,
                 "type":"",
                 "visible":true,
                 "width":32,
                 "x":568,
                 "y":176
                }, 
                {
                 "gid":2147492516,
                 "height":16,
                 "id":930,
                 "name":"",
                 "properties":
                    {
                     "parameters":"{ \"treasurePools\" : [ \"atprk_krakothlabTreasure\" ] }"
                    },
                 "propertytypes":
                    {
                     "parameters":"string"
                    },
                 "rotation":0,
                 "type":"",
                 "visible":true,
                 "width":24,
                 "x":440,
                 "y":176
                }, 
                {
                 "height":120,
                 "id":931,
                 "name":"",
                 "properties":
                    {
                     "parameters":"{\"locationType\":\"atprk_krakothlab.atprk_krakothlabroom3\"}",
                     "stagehand":"questlocation"
                    },
                 "propertytypes":
                    {
                     "parameters":"string",
                     "stagehand":"string"
                    },
                 "rotation":0,
                 "type":"",
                 "visible":true,
                 "width":88,
                 "x":384,
                 "y":56
                }, 
                {
                 "gid":8847,
                 "height":16,
                 "id":932,
                 "name":"",
                 "rotation":0,
                 "type":"",
                 "visible":true,
                 "width":16,
                 "x":264,
                 "y":88
                }],
         "opacity":1,
         "type":"objectgroup",
         "visible":true,
         "x":0,
         "y":0
        }, 
        {
         "color":"#ffff00",
         "draworder":"topdown",
         "name":"wiring - lights & guns",
         "objects":[],
         "opacity":1,
         "type":"objectgroup",
         "visible":true,
         "x":0,
         "y":0
        }, 
        {
         "color":"#ff0000",
         "draworder":"topdown",
         "name":"monsters & npcs",
         "objects":[],
         "opacity":1,
         "type":"objectgroup",
         "visible":true,
         "x":0,
         "y":0
        }, 
        {
         "color":"#00ffff",
         "draworder":"topdown",
         "name":"wiring - locked door",
         "objects":[],
         "opacity":1,
         "type":"objectgroup",
         "visible":true,
         "x":0,
         "y":0
        }, 
        {
         "draworder":"topdown",
         "name":"outside the map",
         "objects":[],
         "opacity":1,
         "type":"objectgroup",
         "visible":true,
         "x":0,
         "y":0
        }, 
        {
         "draworder":"topdown",
         "name":"anchors etc",
         "objects":[
                {
                 "gid":248,
                 "height":8,
                 "id":861,
                 "name":"",
                 "rotation":0,
                 "type":"",
                 "visible":true,
                 "width":8,
                 "x":16,
                 "y":144
                }],
         "opacity":1,
         "type":"objectgroup",
         "visible":true,
         "x":0,
         "y":0
        }, 
        {
         "draworder":"topdown",
         "name":"items",
         "objects":[],
         "opacity":1,
         "type":"objectgroup",
         "visible":true,
         "x":0,
         "y":0
        }],
 "nextobjectid":933,
 "orientation":"orthogonal",
 "renderorder":"right-down",
 "tiledversion":"1.1.1",
 "tileheight":8,
 "tilesets":[
        {
         "firstgid":1,
         "source":"..\/..\/..\/tilesets\/packed\/materials.json"
        }, 
        {
         "firstgid":198,
         "source":"..\/..\/..\/tilesets\/packed\/supports.json"
        }, 
        {
         "firstgid":235,
         "source":"..\/..\/..\/tilesets\/packed\/miscellaneous.json"
        }, 
        {
         "firstgid":259,
         "source":"..\/..\/..\/tilesets\/packed\/liquids.json"
        }, 
        {
         "firstgid":287,
         "source":"..\/..\/..\/tilesets\/packed\/objects-by-race\/generic.json"
        }, 
        {
         "firstgid":2271,
         "source":"..\/..\/..\/tilesets\/packed\/objects-by-race\/ancient.json"
        }, 
        {
         "firstgid":2434,
         "source":"..\/..\/..\/tilesets\/packed\/objects-by-race\/apex.json"
        }, 
        {
         "firstgid":2805,
         "source":"..\/..\/..\/tilesets\/packed\/objects-by-race\/avian.json"
        }, 
        {
         "firstgid":3110,
         "source":"..\/..\/..\/tilesets\/packed\/objects-by-race\/floran.json"
        }, 
        {
         "firstgid":3305,
         "source":"..\/..\/..\/tilesets\/packed\/objects-by-race\/glitch.json"
        }, 
        {
         "firstgid":3531,
         "source":"..\/..\/..\/tilesets\/packed\/objects-by-race\/human.json"
        }, 
        {
         "firstgid":3819,
         "source":"..\/..\/..\/tilesets\/packed\/objects-by-race\/hylotl.json"
        }, 
        {
         "firstgid":4051,
         "source":"..\/..\/..\/tilesets\/packed\/objects-by-race\/novakid.json"
        }, 
        {
         "firstgid":4115,
         "source":"..\/..\/..\/tilesets\/packed\/objects-by-category\/crafting.json"
        }, 
        {
         "firstgid":4195,
         "source":"..\/..\/..\/tilesets\/packed\/objects-by-category\/decorative.json"
        }, 
        {
         "firstgid":5636,
         "source":"..\/..\/..\/tilesets\/packed\/objects-by-category\/door.json"
        }, 
        {
         "firstgid":5768,
         "source":"..\/..\/..\/tilesets\/packed\/objects-by-category\/farmable.json"
        }, 
        {
         "firstgid":5843,
         "source":"..\/..\/..\/tilesets\/packed\/objects-by-category\/furniture.json"
        }, 
        {
         "firstgid":6197,
         "source":"..\/..\/..\/tilesets\/packed\/objects-by-category\/light.json"
        }, 
        {
         "firstgid":6655,
         "source":"..\/..\/..\/tilesets\/packed\/objects-by-category\/other.json"
        }, 
        {
         "firstgid":6967,
         "source":"..\/..\/..\/tilesets\/packed\/objects-by-category\/pot.json"
        }, 
        {
         "firstgid":7264,
         "source":"..\/..\/..\/tilesets\/packed\/objects-by-category\/sapling.json"
        }, 
        {
         "firstgid":7265,
         "source":"..\/..\/..\/tilesets\/packed\/objects-by-category\/spawner.json"
        }, 
        {
         "firstgid":7281,
         "source":"..\/..\/..\/tilesets\/packed\/objects-by-category\/storage.json"
        }, 
        {
         "firstgid":7515,
         "source":"..\/..\/..\/tilesets\/packed\/objects-by-category\/teleporter.json"
        }, 
        {
         "firstgid":7557,
         "source":"..\/..\/..\/tilesets\/packed\/objects-by-category\/tools.json"
        }, 
        {
         "firstgid":7562,
         "source":"..\/..\/..\/tilesets\/packed\/objects-by-category\/trap.json"
        }, 
        {
         "firstgid":7766,
         "source":"..\/..\/..\/tilesets\/packed\/objects-by-category\/wire.json"
        }, 
        {
         "firstgid":7988,
         "source":"..\/..\/..\/tilesets\/packed\/objects-by-type\/container.json"
        }, 
        {
         "firstgid":8273,
         "source":"..\/..\/..\/tilesets\/packed\/objects-by-type\/farmable.json"
        }, 
        {
         "firstgid":8351,
         "source":"..\/..\/..\/tilesets\/packed\/objects-by-type\/loungeable.json"
        }, 
        {
         "firstgid":8632,
         "source":"..\/..\/..\/tilesets\/packed\/objects-by-type\/noisy.json"
        }, 
        {
         "firstgid":8673,
         "source":"..\/..\/..\/tilesets\/packed\/objects-by-type\/teleporter.json"
        }, 
        {
         "firstgid":8700,
         "source":"..\/..\/..\/tilesets\/packed\/huge-objects.json"
        }, 
        {
         "firstgid":8801,
         "source":"..\/..\/..\/..\/..\/mods\/precursorracekrakoth\/tilesets\/precursorracekrakoth_custom\/atprk-krakothdungeonset3.json"
        }, 
        {
         "firstgid":8859,
         "source":"..\/..\/..\/..\/..\/mods\/precursorracekrakoth\/tilesets\/precursorracekrakoth_custom\/atprk-krakothdungeonset1.json"
        }],
 "tilewidth":8,
 "type":"map",
 "version":1,
 "width":90
}